{
"STAOU": "stew",
"SKAEUR": "scare",
"SKAEUT": "skate",
"SKAR": "scar",
"SKAB": "scab",
"SKAT": "scat",
"SKOER": "score",
"SKOF": "scoff",
"SKEUP": "skip",
"SKEUL": "skill",
"SKEUT": "skit",
"SKEUD": "skid",
"SKUF": "scuff",
"SKUL": "skull",
"SPH-F": "some of",
"SPH-FT": "some of the",
"SHRAOEUGT": "slight",
"SHRAOEUS": "slice",
"SHRAOEUD": "slide",
"SHRAOEP": "sleep",
"SHRAOET": "sleet",
"SHRAP": "slap",
"SHRAB": "slab",
"SHRAT": "slat",
"SHROE": "slow",
"SHROP": "slop",
"SHROB": "slob",
"SHROT": "slot",
"SHREUP": "slip",
"SHREUT": "slit",
"SHREUD": "slid",
"SHRUR": "slur",
"SHRURP": "slurp",
"SHRUG": "slug",
"SHRUT": "slut",
"SR": "have",
"SRA": "have a",
"SRAOEU": "vie",
"SRAOEUS": "vice",
"SRAOU": "view",
"SRAEUL": "veil",
"SRAEUG": "vague",
"SRAEUS": "vase",
"SRAT": "vat",
"SROEG": "vogue",
"SROET": "vote",
"SRE": "very",
"SRET": "vet",
"SRU": "have you",
"SR-T": "have the",
"SAO*U": "Sue",
"SAOEUD": "side",
"SAOEUZ": "size",
"SAOUP": "soup",
"SAEUF": "safe",
"SED": "said",
"TKAOEU": "die",
"TKA*D": "Dad",
"TKAEL": "deal",
"TK*UG": "Doug",
"TP": "if",
"TPHAOEUS": "nice",
"TPAOEUR": "fire",
"TPAOEUL": "file",
"TPAOEUGT": "fight",
"TPAOEL": "feel",
"TPAOET": "feet",
"TPAOED": "feed",
"TPAOUL": "fuel",
"TPAEUL": "fail",
"TPAEUT": "fate",
"TPAEUS": "face",
"TPAEUZ": "phase",
"TPAER": "fear",
"TPAET": "feat",
"TPAR": "far",
"TPAT": "fat",
"TPO": "inform",
"TPOE": "foe",
"TPOERT": "fort",
"TPOU": "inform you",
"TPOUS": "inform us",
"TPOR": "for",
"TPORT": "for the",
"TPOG": "fog",
"TPOGS": "information",
"TP*EUL": "Phil",
"TPE": "if he",
"TPEU": "if I",
"TPEUL": "fill",
"TPEUT": "fit",
"TPEL": "fell",
"TPED": "fed",
"TPU": "if you",
"TPUL": "full",
"TP-T": "if the",
"TOER": "tore",
"KWRUR": "your",
"PAOEU": "pie",
"PAOEUP": "pipe",
"PAOR": "poor",
"PO*ER": "pore",
"POER": "pour",
"POUR": "power",
"PEUG": "pig",
"WHO": "who",
"WOER": "wore",
"HAOEUR": "hire",
"HOG": "hog",
"OFT": "off the",
"EUB": "I be",
"-FT": "of the"
}
